{
  "concept_code": "301546",
  "concept_name": "央企国企改革",
  "first_trade_date": "2015-01-05",
  "latest_trade_date": "2026-07-09",
  "constituent_count": 394,
  "constituents": [
    {
      "code": "bj.920029",
      "raw_code": "920029",
      "name": "开发科技"
    },
    {
      "code": "bj.920122",
      "raw_code": "920122",
      "name": "中纺标"
    },
    {
      "code": "bj.920160",
      "raw_code": "920160",
      "name": "北矿检测"
    },
    {
      "code": "bj.920579",
      "raw_code": "920579",
      "name": "机科股份"
    },
    {
      "code": "bj.920640",
      "raw_code": "920640",
      "name": "富士达"
    },
    {
      "code": "sh.600006",
      "raw_code": "600006",
      "name": "东风股份"
    },
    {
      "code": "sh.600011",
      "raw_code": "600011",
      "name": "华能国际"
    },
    {
      "code": "sh.600019",
      "raw_code": "600019",
      "name": "宝钢股份"
    },
    {
      "code": "sh.600021",
      "raw_code": "600021",
      "name": "上海电力"
    },
    {
      "code": "sh.600025",
      "raw_code": "600025",
      "name": "华能水电"
    },
    {
      "code": "sh.600026",
      "raw_code": "600026",
      "name": "中远海能"
    },
    {
      "code": "sh.600027",
      "raw_code": "600027",
      "name": "华电国际"
    },
    {
      "code": "sh.600028",
      "raw_code": "600028",
      "name": "中国石化"
    },
    {
      "code": "sh.600029",
      "raw_code": "600029",
      "name": "南方航空"
    },
    {
      "code": "sh.600037",
      "raw_code": "600037",
      "name": "歌华有线"
    },
    {
      "code": "sh.600038",
      "raw_code": "600038",
      "name": "中直股份"
    },
    {
      "code": "sh.600048",
      "raw_code": "600048",
      "name": "保利发展"
    },
    {
      "code": "sh.600050",
      "raw_code": "600050",
      "name": "中国联通"
    },
    {
      "code": "sh.600056",
      "raw_code": "600056",
      "name": "中国医药"
    },
    {
      "code": "sh.600058",
      "raw_code": "600058",
      "name": "五矿发展"
    },
    {
      "code": "sh.600061",
      "raw_code": "600061",
      "name": "国投资本"
    },
    {
      "code": "sh.600062",
      "raw_code": "600062",
      "name": "华润双鹤"
    },
    {
      "code": "sh.600071",
      "raw_code": "600071",
      "name": "凤凰光学"
    },
    {
      "code": "sh.600072",
      "raw_code": "600072",
      "name": "中船科技"
    },
    {
      "code": "sh.600079",
      "raw_code": "600079",
      "name": "ST人福"
    },
    {
      "code": "sh.600099",
      "raw_code": "600099",
      "name": "林海股份"
    },
    {
      "code": "sh.600100",
      "raw_code": "600100",
      "name": "同方股份"
    },
    {
      "code": "sh.600101",
      "raw_code": "600101",
      "name": "明星电力"
    },
    {
      "code": "sh.600115",
      "raw_code": "600115",
      "name": "中国东航"
    },
    {
      "code": "sh.600116",
      "raw_code": "600116",
      "name": "三峡水利"
    },
    {
      "code": "sh.600118",
      "raw_code": "600118",
      "name": "中国卫星"
    },
    {
      "code": "sh.600129",
      "raw_code": "600129",
      "name": "太极集团"
    },
    {
      "code": "sh.600131",
      "raw_code": "600131",
      "name": "国网信通"
    },
    {
      "code": "sh.600135",
      "raw_code": "600135",
      "name": "乐凯胶片"
    },
    {
      "code": "sh.600138",
      "raw_code": "600138",
      "name": "中青旅"
    },
    {
      "code": "sh.600148",
      "raw_code": "600148",
      "name": "长春一东"
    },
    {
      "code": "sh.600150",
      "raw_code": "600150",
      "name": "中国船舶"
    },
    {
      "code": "sh.600151",
      "raw_code": "600151",
      "name": "航天机电"
    },
    {
      "code": "sh.600161",
      "raw_code": "600161",
      "name": "天坛生物"
    },
    {
      "code": "sh.600171",
      "raw_code": "600171",
      "name": "上海贝岭"
    },
    {
      "code": "sh.600176",
      "raw_code": "600176",
      "name": "中国巨石"
    },
    {
      "code": "sh.600178",
      "raw_code": "600178",
      "name": "东安动力"
    },
    {
      "code": "sh.600184",
      "raw_code": "600184",
      "name": "光电股份"
    },
    {
      "code": "sh.600195",
      "raw_code": "600195",
      "name": "中牧股份"
    },
    {
      "code": "sh.600198",
      "raw_code": "600198",
      "name": "大唐电信"
    },
    {
      "code": "sh.600206",
      "raw_code": "600206",
      "name": "有研新材"
    },
    {
      "code": "sh.600230",
      "raw_code": "600230",
      "name": "沧州大化"
    },
    {
      "code": "sh.600231",
      "raw_code": "600231",
      "name": "凌钢股份"
    },
    {
      "code": "sh.600236",
      "raw_code": "600236",
      "name": "桂冠电力"
    },
    {
      "code": "sh.600259",
      "raw_code": "600259",
      "name": "中稀有色"
    },
    {
      "code": "sh.600262",
      "raw_code": "600262",
      "name": "北方股份"
    },
    {
      "code": "sh.600268",
      "raw_code": "600268",
      "name": "国电南自"
    },
    {
      "code": "sh.600271",
      "raw_code": "600271",
      "name": "航天信息"
    },
    {
      "code": "sh.600292",
      "raw_code": "600292",
      "name": "电投水电"
    },
    {
      "code": "sh.600299",
      "raw_code": "600299",
      "name": "安迪苏"
    },
    {
      "code": "sh.600312",
      "raw_code": "600312",
      "name": "平高电气"
    },
    {
      "code": "sh.600313",
      "raw_code": "600313",
      "name": "农发种业"
    },
    {
      "code": "sh.600316",
      "raw_code": "600316",
      "name": "洪都航空"
    },
    {
      "code": "sh.600320",
      "raw_code": "600320",
      "name": "振华重工"
    },
    {
      "code": "sh.600328",
      "raw_code": "600328",
      "name": "中盐化工"
    },
    {
      "code": "sh.600335",
      "raw_code": "600335",
      "name": "国机汽车"
    },
    {
      "code": "sh.600343",
      "raw_code": "600343",
      "name": "航天动力"
    },
    {
      "code": "sh.600345",
      "raw_code": "600345",
      "name": "长江通信"
    },
    {
      "code": "sh.600372",
      "raw_code": "600372",
      "name": "中航机载"
    },
    {
      "code": "sh.600378",
      "raw_code": "600378",
      "name": "昊华科技"
    },
    {
      "code": "sh.600379",
      "raw_code": "600379",
      "name": "宝光股份"
    },
    {
      "code": "sh.600390",
      "raw_code": "600390",
      "name": "五矿资本"
    },
    {
      "code": "sh.600391",
      "raw_code": "600391",
      "name": "航发科技"
    },
    {
      "code": "sh.600396",
      "raw_code": "600396",
      "name": "华电辽能"
    },
    {
      "code": "sh.600406",
      "raw_code": "600406",
      "name": "国电南瑞"
    },
    {
      "code": "sh.600420",
      "raw_code": "600420",
      "name": "国药现代"
    },
    {
      "code": "sh.600422",
      "raw_code": "600422",
      "name": "昆药集团"
    },
    {
      "code": "sh.600428",
      "raw_code": "600428",
      "name": "中远海特"
    },
    {
      "code": "sh.600433",
      "raw_code": "600433",
      "name": "冠豪高新"
    },
    {
      "code": "sh.600435",
      "raw_code": "600435",
      "name": "北方导航"
    },
    {
      "code": "sh.600444",
      "raw_code": "600444",
      "name": "国机通用"
    },
    {
      "code": "sh.600449",
      "raw_code": "600449",
      "name": "宁夏建材"
    },
    {
      "code": "sh.600452",
      "raw_code": "600452",
      "name": "涪陵电力"
    },
    {
      "code": "sh.600458",
      "raw_code": "600458",
      "name": "时代新材"
    },
    {
      "code": "sh.600469",
      "raw_code": "600469",
      "name": "风神股份"
    },
    {
      "code": "sh.600476",
      "raw_code": "600476",
      "name": "*ST湘邮"
    },
    {
      "code": "sh.600480",
      "raw_code": "600480",
      "name": "凌云股份"
    },
    {
      "code": "sh.600482",
      "raw_code": "600482",
      "name": "中国动力"
    },
    {
      "code": "sh.600486",
      "raw_code": "600486",
      "name": "扬农化工"
    },
    {
      "code": "sh.600489",
      "raw_code": "600489",
      "name": "中金黄金"
    },
    {
      "code": "sh.600495",
      "raw_code": "600495",
      "name": "晋西车轴"
    },
    {
      "code": "sh.600497",
      "raw_code": "600497",
      "name": "驰宏锌锗"
    },
    {
      "code": "sh.600498",
      "raw_code": "600498",
      "name": "烽火通信"
    },
    {
      "code": "sh.600500",
      "raw_code": "600500",
      "name": "中化国际"
    },
    {
      "code": "sh.600501",
      "raw_code": "600501",
      "name": "航天晨光"
    },
    {
      "code": "sh.600505",
      "raw_code": "600505",
      "name": "西昌电力"
    },
    {
      "code": "sh.600506",
      "raw_code": "600506",
      "name": "统一股份"
    },
    {
      "code": "sh.600508",
      "raw_code": "600508",
      "name": "上海能源"
    },
    {
      "code": "sh.600511",
      "raw_code": "600511",
      "name": "国药股份"
    },
    {
      "code": "sh.600517",
      "raw_code": "600517",
      "name": "国网英大"
    },
    {
      "code": "sh.600523",
      "raw_code": "600523",
      "name": "贵航股份"
    },
    {
      "code": "sh.600528",
      "raw_code": "600528",
      "name": "中铁工业"
    },
    {
      "code": "sh.600535",
      "raw_code": "600535",
      "name": "天士力"
    },
    {
      "code": "sh.600536",
      "raw_code": "600536",
      "name": "中国软件"
    },
    {
      "code": "sh.600550",
      "raw_code": "600550",
      "name": "保变电气"
    },
    {
      "code": "sh.600552",
      "raw_code": "600552",
      "name": "凯盛科技"
    },
    {
      "code": "sh.600560",
      "raw_code": "600560",
      "name": "金自天正"
    },
    {
      "code": "sh.600562",
      "raw_code": "600562",
      "name": "国睿科技"
    },
    {
      "code": "sh.600579",
      "raw_code": "600579",
      "name": "中化装备"
    },
    {
      "code": "sh.600581",
      "raw_code": "600581",
      "name": "*ST八钢"
    },
    {
      "code": "sh.600582",
      "raw_code": "600582",
      "name": "天地科技"
    },
    {
      "code": "sh.600583",
      "raw_code": "600583",
      "name": "海油工程"
    },
    {
      "code": "sh.600584",
      "raw_code": "600584",
      "name": "长电科技"
    },
    {
      "code": "sh.600640",
      "raw_code": "600640",
      "name": "国脉文化"
    },
    {
      "code": "sh.600657",
      "raw_code": "600657",
      "name": "信达地产"
    },
    {
      "code": "sh.600685",
      "raw_code": "600685",
      "name": "中船防务"
    },
    {
      "code": "sh.600688",
      "raw_code": "600688",
      "name": "上海石化"
    },
    {
      "code": "sh.600698",
      "raw_code": "600698",
      "name": "湖南天雁"
    },
    {
      "code": "sh.600710",
      "raw_code": "600710",
      "name": "苏美达"
    },
    {
      "code": "sh.600714",
      "raw_code": "600714",
      "name": "金瑞矿业"
    },
    {
      "code": "sh.600720",
      "raw_code": "600720",
      "name": "中交设计"
    },
    {
      "code": "sh.600726",
      "raw_code": "600726",
      "name": "华电能源"
    },
    {
      "code": "sh.600737",
      "raw_code": "600737",
      "name": "中粮糖业"
    },
    {
      "code": "sh.600744",
      "raw_code": "600744",
      "name": "华银电力"
    },
    {
      "code": "sh.600750",
      "raw_code": "600750",
      "name": "华润江中"
    },
    {
      "code": "sh.600760",
      "raw_code": "600760",
      "name": "中航沈飞"
    },
    {
      "code": "sh.600764",
      "raw_code": "600764",
      "name": "中国海防"
    },
    {
      "code": "sh.600765",
      "raw_code": "600765",
      "name": "中航重机"
    },
    {
      "code": "sh.600775",
      "raw_code": "600775",
      "name": "南京熊猫"
    },
    {
      "code": "sh.600776",
      "raw_code": "600776",
      "name": "东方通信"
    },
    {
      "code": "sh.600782",
      "raw_code": "600782",
      "name": "新钢股份"
    },
    {
      "code": "sh.600787",
      "raw_code": "600787",
      "name": "中储股份"
    },
    {
      "code": "sh.600795",
      "raw_code": "600795",
      "name": "国电电力"
    },
    {
      "code": "sh.600808",
      "raw_code": "600808",
      "name": "马钢股份"
    },
    {
      "code": "sh.600845",
      "raw_code": "600845",
      "name": "宝信软件"
    },
    {
      "code": "sh.600850",
      "raw_code": "600850",
      "name": "电科数字"
    },
    {
      "code": "sh.600855",
      "raw_code": "600855",
      "name": "航天长峰"
    },
    {
      "code": "sh.600862",
      "raw_code": "600862",
      "name": "中航高科"
    },
    {
      "code": "sh.600863",
      "raw_code": "600863",
      "name": "华能蒙电"
    },
    {
      "code": "sh.600871",
      "raw_code": "600871",
      "name": "石化油服"
    },
    {
      "code": "sh.600875",
      "raw_code": "600875",
      "name": "东方电气"
    },
    {
      "code": "sh.600876",
      "raw_code": "600876",
      "name": "凯盛新能"
    },
    {
      "code": "sh.600877",
      "raw_code": "600877",
      "name": "电科芯片"
    },
    {
      "code": "sh.600879",
      "raw_code": "600879",
      "name": "航天电子"
    },
    {
      "code": "sh.600886",
      "raw_code": "600886",
      "name": "国投电力"
    },
    {
      "code": "sh.600893",
      "raw_code": "600893",
      "name": "航发动力"
    },
    {
      "code": "sh.600900",
      "raw_code": "600900",
      "name": "长江电力"
    },
    {
      "code": "sh.600905",
      "raw_code": "600905",
      "name": "三峡能源"
    },
    {
      "code": "sh.600916",
      "raw_code": "600916",
      "name": "中国黄金"
    },
    {
      "code": "sh.600917",
      "raw_code": "600917",
      "name": "重庆燃气"
    },
    {
      "code": "sh.600930",
      "raw_code": "600930",
      "name": "华电新能"
    },
    {
      "code": "sh.600938",
      "raw_code": "600938",
      "name": "中国海油"
    },
    {
      "code": "sh.600961",
      "raw_code": "600961",
      "name": "株冶集团"
    },
    {
      "code": "sh.600962",
      "raw_code": "600962",
      "name": "国投中鲁"
    },
    {
      "code": "sh.600963",
      "raw_code": "600963",
      "name": "岳阳林纸"
    },
    {
      "code": "sh.600967",
      "raw_code": "600967",
      "name": "内蒙一机"
    },
    {
      "code": "sh.600970",
      "raw_code": "600970",
      "name": "中材国际"
    },
    {
      "code": "sh.600973",
      "raw_code": "600973",
      "name": "宝胜股份"
    },
    {
      "code": "sh.600980",
      "raw_code": "600980",
      "name": "北矿科技"
    },
    {
      "code": "sh.600990",
      "raw_code": "600990",
      "name": "四创电子"
    },
    {
      "code": "sh.600995",
      "raw_code": "600995",
      "name": "南网储能"
    },
    {
      "code": "sh.600999",
      "raw_code": "600999",
      "name": "招商证券"
    },
    {
      "code": "sh.601005",
      "raw_code": "601005",
      "name": "重庆钢铁"
    },
    {
      "code": "sh.601016",
      "raw_code": "601016",
      "name": "节能风电"
    },
    {
      "code": "sh.601038",
      "raw_code": "601038",
      "name": "一拖股份"
    },
    {
      "code": "sh.601059",
      "raw_code": "601059",
      "name": "信达证券"
    },
    {
      "code": "sh.601068",
      "raw_code": "601068",
      "name": "中铝国际"
    },
    {
      "code": "sh.601088",
      "raw_code": "601088",
      "name": "中国神华"
    },
    {
      "code": "sh.601096",
      "raw_code": "601096",
      "name": "宏盛华源"
    },
    {
      "code": "sh.601106",
      "raw_code": "601106",
      "name": "中国一重"
    },
    {
      "code": "sh.601111",
      "raw_code": "601111",
      "name": "中国国航"
    },
    {
      "code": "sh.601117",
      "raw_code": "601117",
      "name": "中国化学"
    },
    {
      "code": "sh.601156",
      "raw_code": "601156",
      "name": "东航物流"
    },
    {
      "code": "sh.601179",
      "raw_code": "601179",
      "name": "中国西电"
    },
    {
      "code": "sh.601186",
      "raw_code": "601186",
      "name": "中国铁建"
    },
    {
      "code": "sh.601198",
      "raw_code": "601198",
      "name": "东兴证券"
    },
    {
      "code": "sh.601226",
      "raw_code": "601226",
      "name": "华电科工"
    },
    {
      "code": "sh.601390",
      "raw_code": "601390",
      "name": "中国中铁"
    },
    {
      "code": "sh.601399",
      "raw_code": "601399",
      "name": "国机重装"
    },
    {
      "code": "sh.601598",
      "raw_code": "601598",
      "name": "中国外运"
    },
    {
      "code": "sh.601600",
      "raw_code": "601600",
      "name": "中国铝业"
    },
    {
      "code": "sh.601606",
      "raw_code": "601606",
      "name": "长城军工"
    },
    {
      "code": "sh.601611",
      "raw_code": "601611",
      "name": "中国核建"
    },
    {
      "code": "sh.601618",
      "raw_code": "601618",
      "name": "中国中冶"
    },
    {
      "code": "sh.601668",
      "raw_code": "601668",
      "name": "中国建筑"
    },
    {
      "code": "sh.601669",
      "raw_code": "601669",
      "name": "中国电建"
    },
    {
      "code": "sh.601698",
      "raw_code": "601698",
      "name": "中国卫通"
    },
    {
      "code": "sh.601718",
      "raw_code": "601718",
      "name": "ST际华"
    },
    {
      "code": "sh.601728",
      "raw_code": "601728",
      "name": "中国电信"
    },
    {
      "code": "sh.601766",
      "raw_code": "601766",
      "name": "中国中车"
    },
    {
      "code": "sh.601788",
      "raw_code": "601788",
      "name": "光大证券"
    },
    {
      "code": "sh.601798",
      "raw_code": "601798",
      "name": "蓝科高新"
    },
    {
      "code": "sh.601800",
      "raw_code": "601800",
      "name": "中国交建"
    },
    {
      "code": "sh.601808",
      "raw_code": "601808",
      "name": "中海油服"
    },
    {
      "code": "sh.601857",
      "raw_code": "601857",
      "name": "中国石油"
    },
    {
      "code": "sh.601866",
      "raw_code": "601866",
      "name": "中远海发"
    },
    {
      "code": "sh.601868",
      "raw_code": "601868",
      "name": "中国能建"
    },
    {
      "code": "sh.601872",
      "raw_code": "601872",
      "name": "招商轮船"
    },
    {
      "code": "sh.601888",
      "raw_code": "601888",
      "name": "中国中免"
    },
    {
      "code": "sh.601898",
      "raw_code": "601898",
      "name": "中煤能源"
    },
    {
      "code": "sh.601918",
      "raw_code": "601918",
      "name": "新集能源"
    },
    {
      "code": "sh.601919",
      "raw_code": "601919",
      "name": "中远海控"
    },
    {
      "code": "sh.601965",
      "raw_code": "601965",
      "name": "中国汽研"
    },
    {
      "code": "sh.601968",
      "raw_code": "601968",
      "name": "宝钢包装"
    },
    {
      "code": "sh.601975",
      "raw_code": "601975",
      "name": "招商南油"
    },
    {
      "code": "sh.601985",
      "raw_code": "601985",
      "name": "中国核电"
    },
    {
      "code": "sh.601991",
      "raw_code": "601991",
      "name": "大唐发电"
    },
    {
      "code": "sh.603060",
      "raw_code": "603060",
      "name": "国检集团"
    },
    {
      "code": "sh.603082",
      "raw_code": "603082",
      "name": "北自科技"
    },
    {
      "code": "sh.603100",
      "raw_code": "603100",
      "name": "川仪股份"
    },
    {
      "code": "sh.603126",
      "raw_code": "603126",
      "name": "中材节能"
    },
    {
      "code": "sh.603128",
      "raw_code": "603128",
      "name": "华贸物流"
    },
    {
      "code": "sh.603395",
      "raw_code": "603395",
      "name": "红四方"
    },
    {
      "code": "sh.688009",
      "raw_code": "688009",
      "name": "中国通号"
    },
    {
      "code": "sh.688027",
      "raw_code": "688027",
      "name": "国盾量子"
    },
    {
      "code": "sh.688119",
      "raw_code": "688119",
      "name": "中钢洛耐"
    },
    {
      "code": "sh.688128",
      "raw_code": "688128",
      "name": "中国电研"
    },
    {
      "code": "sh.688146",
      "raw_code": "688146",
      "name": "中船特气"
    },
    {
      "code": "sh.688151",
      "raw_code": "688151",
      "name": "华强科技"
    },
    {
      "code": "sh.688187",
      "raw_code": "688187",
      "name": "时代电气"
    },
    {
      "code": "sh.688190",
      "raw_code": "688190",
      "name": "云路股份"
    },
    {
      "code": "sh.688248",
      "raw_code": "688248",
      "name": "南网科技"
    },
    {
      "code": "sh.688285",
      "raw_code": "688285",
      "name": "高铁电气"
    },
    {
      "code": "sh.688297",
      "raw_code": "688297",
      "name": "中无人机"
    },
    {
      "code": "sh.688334",
      "raw_code": "688334",
      "name": "西高院"
    },
    {
      "code": "sh.688375",
      "raw_code": "688375",
      "name": "国博电子"
    },
    {
      "code": "sh.688387",
      "raw_code": "688387",
      "name": "信科移动"
    },
    {
      "code": "sh.688396",
      "raw_code": "688396",
      "name": "华润微"
    },
    {
      "code": "sh.688425",
      "raw_code": "688425",
      "name": "铁建重工"
    },
    {
      "code": "sh.688439",
      "raw_code": "688439",
      "name": "振华风光"
    },
    {
      "code": "sh.688456",
      "raw_code": "688456",
      "name": "有研粉材"
    },
    {
      "code": "sh.688509",
      "raw_code": "688509",
      "name": "正元地信"
    },
    {
      "code": "sh.688552",
      "raw_code": "688552",
      "name": "航天南湖"
    },
    {
      "code": "sh.688562",
      "raw_code": "688562",
      "name": "航天软件"
    },
    {
      "code": "sh.688563",
      "raw_code": "688563",
      "name": "航材股份"
    },
    {
      "code": "sh.688569",
      "raw_code": "688569",
      "name": "铁科轨道"
    },
    {
      "code": "sh.688570",
      "raw_code": "688570",
      "name": "天玛智控"
    },
    {
      "code": "sh.688586",
      "raw_code": "688586",
      "name": "江航装备"
    },
    {
      "code": "sh.688631",
      "raw_code": "688631",
      "name": "莱斯信息"
    },
    {
      "code": "sh.688707",
      "raw_code": "688707",
      "name": "振华新材"
    },
    {
      "code": "sh.688709",
      "raw_code": "688709",
      "name": "成都华微"
    },
    {
      "code": "sh.688710",
      "raw_code": "688710",
      "name": "益诺思"
    },
    {
      "code": "sh.688722",
      "raw_code": "688722",
      "name": "同益中"
    },
    {
      "code": "sh.688779",
      "raw_code": "688779",
      "name": "五矿新能"
    },
    {
      "code": "sh.688811",
      "raw_code": "688811",
      "name": "有研复材"
    },
    {
      "code": "sh.688818",
      "raw_code": "688818",
      "name": "电科蓝天"
    },
    {
      "code": "sz.000008",
      "raw_code": "000008",
      "name": "神州高铁"
    },
    {
      "code": "sz.000016",
      "raw_code": "000016",
      "name": "*ST康佳A"
    },
    {
      "code": "sz.000021",
      "raw_code": "000021",
      "name": "深科技"
    },
    {
      "code": "sz.000026",
      "raw_code": "000026",
      "name": "飞亚达"
    },
    {
      "code": "sz.000028",
      "raw_code": "000028",
      "name": "国药一致"
    },
    {
      "code": "sz.000031",
      "raw_code": "000031",
      "name": "大悦城"
    },
    {
      "code": "sz.000032",
      "raw_code": "000032",
      "name": "深桑达A"
    },
    {
      "code": "sz.000050",
      "raw_code": "000050",
      "name": "深天马A"
    },
    {
      "code": "sz.000059",
      "raw_code": "000059",
      "name": "华锦股份"
    },
    {
      "code": "sz.000065",
      "raw_code": "000065",
      "name": "北方国际"
    },
    {
      "code": "sz.000066",
      "raw_code": "000066",
      "name": "中国长城"
    },
    {
      "code": "sz.000069",
      "raw_code": "000069",
      "name": "华侨城A"
    },
    {
      "code": "sz.000151",
      "raw_code": "000151",
      "name": "中成股份"
    },
    {
      "code": "sz.000400",
      "raw_code": "000400",
      "name": "许继电气"
    },
    {
      "code": "sz.000410",
      "raw_code": "000410",
      "name": "沈阳机床"
    },
    {
      "code": "sz.000423",
      "raw_code": "000423",
      "name": "东阿阿胶"
    },
    {
      "code": "sz.000503",
      "raw_code": "000503",
      "name": "国新健康"
    },
    {
      "code": "sz.000519",
      "raw_code": "000519",
      "name": "中兵红箭"
    },
    {
      "code": "sz.000537",
      "raw_code": "000537",
      "name": "绿发电力"
    },
    {
      "code": "sz.000547",
      "raw_code": "000547",
      "name": "航天发展"
    },
    {
      "code": "sz.000550",
      "raw_code": "000550",
      "name": "江铃汽车"
    },
    {
      "code": "sz.000553",
      "raw_code": "000553",
      "name": "安道麦A"
    },
    {
      "code": "sz.000554",
      "raw_code": "000554",
      "name": "泰山石油"
    },
    {
      "code": "sz.000566",
      "raw_code": "000566",
      "name": "海南海药"
    },
    {
      "code": "sz.000591",
      "raw_code": "000591",
      "name": "太阳能"
    },
    {
      "code": "sz.000625",
      "raw_code": "000625",
      "name": "长安汽车"
    },
    {
      "code": "sz.000635",
      "raw_code": "000635",
      "name": "英力特"
    },
    {
      "code": "sz.000663",
      "raw_code": "000663",
      "name": "永安林业"
    },
    {
      "code": "sz.000698",
      "raw_code": "000698",
      "name": "ST沈化"
    },
    {
      "code": "sz.000713",
      "raw_code": "000713",
      "name": "国投丰乐"
    },
    {
      "code": "sz.000717",
      "raw_code": "000717",
      "name": "中南股份"
    },
    {
      "code": "sz.000720",
      "raw_code": "000720",
      "name": "新能泰山"
    },
    {
      "code": "sz.000727",
      "raw_code": "000727",
      "name": "冠捷科技"
    },
    {
      "code": "sz.000731",
      "raw_code": "000731",
      "name": "四川美丰"
    },
    {
      "code": "sz.000733",
      "raw_code": "000733",
      "name": "振华科技"
    },
    {
      "code": "sz.000736",
      "raw_code": "000736",
      "name": "中交发展"
    },
    {
      "code": "sz.000738",
      "raw_code": "000738",
      "name": "航发控制"
    },
    {
      "code": "sz.000758",
      "raw_code": "000758",
      "name": "中色股份"
    },
    {
      "code": "sz.000761",
      "raw_code": "000761",
      "name": "本钢板材"
    },
    {
      "code": "sz.000762",
      "raw_code": "000762",
      "name": "西藏矿业"
    },
    {
      "code": "sz.000768",
      "raw_code": "000768",
      "name": "中航西飞"
    },
    {
      "code": "sz.000777",
      "raw_code": "000777",
      "name": "中核科技"
    },
    {
      "code": "sz.000778",
      "raw_code": "000778",
      "name": "新兴铸管"
    },
    {
      "code": "sz.000786",
      "raw_code": "000786",
      "name": "北新建材"
    },
    {
      "code": "sz.000792",
      "raw_code": "000792",
      "name": "盐湖股份"
    },
    {
      "code": "sz.000798",
      "raw_code": "000798",
      "name": "中水渔业"
    },
    {
      "code": "sz.000799",
      "raw_code": "000799",
      "name": "酒鬼酒"
    },
    {
      "code": "sz.000800",
      "raw_code": "000800",
      "name": "一汽解放"
    },
    {
      "code": "sz.000807",
      "raw_code": "000807",
      "name": "云铝股份"
    },
    {
      "code": "sz.000815",
      "raw_code": "000815",
      "name": "美利云"
    },
    {
      "code": "sz.000819",
      "raw_code": "000819",
      "name": "岳阳兴长"
    },
    {
      "code": "sz.000825",
      "raw_code": "000825",
      "name": "太钢不锈"
    },
    {
      "code": "sz.000830",
      "raw_code": "000830",
      "name": "鲁西化工"
    },
    {
      "code": "sz.000831",
      "raw_code": "000831",
      "name": "中国稀土"
    },
    {
      "code": "sz.000852",
      "raw_code": "000852",
      "name": "石化机械"
    },
    {
      "code": "sz.000862",
      "raw_code": "000862",
      "name": "银星能源"
    },
    {
      "code": "sz.000875",
      "raw_code": "000875",
      "name": "电投绿能"
    },
    {
      "code": "sz.000877",
      "raw_code": "000877",
      "name": "天山股份"
    },
    {
      "code": "sz.000878",
      "raw_code": "000878",
      "name": "云南铜业"
    },
    {
      "code": "sz.000883",
      "raw_code": "000883",
      "name": "湖北能源"
    },
    {
      "code": "sz.000898",
      "raw_code": "000898",
      "name": "鞍钢股份"
    },
    {
      "code": "sz.000901",
      "raw_code": "000901",
      "name": "航天科技"
    },
    {
      "code": "sz.000920",
      "raw_code": "000920",
      "name": "沃顿科技"
    },
    {
      "code": "sz.000922",
      "raw_code": "000922",
      "name": "佳电股份"
    },
    {
      "code": "sz.000927",
      "raw_code": "000927",
      "name": "中国铁物"
    },
    {
      "code": "sz.000928",
      "raw_code": "000928",
      "name": "中钢国际"
    },
    {
      "code": "sz.000930",
      "raw_code": "000930",
      "name": "中粮科技"
    },
    {
      "code": "sz.000950",
      "raw_code": "000950",
      "name": "重药控股"
    },
    {
      "code": "sz.000958",
      "raw_code": "000958",
      "name": "电投产融"
    },
    {
      "code": "sz.000962",
      "raw_code": "000962",
      "name": "东方钽业"
    },
    {
      "code": "sz.000966",
      "raw_code": "000966",
      "name": "长源电力"
    },
    {
      "code": "sz.000969",
      "raw_code": "000969",
      "name": "安泰科技"
    },
    {
      "code": "sz.000985",
      "raw_code": "000985",
      "name": "大庆华科"
    },
    {
      "code": "sz.000999",
      "raw_code": "000999",
      "name": "华润三九"
    },
    {
      "code": "sz.001248",
      "raw_code": "001248",
      "name": "华润新能源"
    },
    {
      "code": "sz.001280",
      "raw_code": "001280",
      "name": "中国铀业"
    },
    {
      "code": "sz.001287",
      "raw_code": "001287",
      "name": "中电港"
    },
    {
      "code": "sz.001289",
      "raw_code": "001289",
      "name": "龙源电力"
    },
    {
      "code": "sz.001391",
      "raw_code": "001391",
      "name": "国货航"
    },
    {
      "code": "sz.001872",
      "raw_code": "001872",
      "name": "招商港口"
    },
    {
      "code": "sz.001914",
      "raw_code": "001914",
      "name": "招商积余"
    },
    {
      "code": "sz.001965",
      "raw_code": "001965",
      "name": "招商公路"
    },
    {
      "code": "sz.001979",
      "raw_code": "001979",
      "name": "招商蛇口"
    },
    {
      "code": "sz.002025",
      "raw_code": "002025",
      "name": "航天电器"
    },
    {
      "code": "sz.002037",
      "raw_code": "002037",
      "name": "保利联合"
    },
    {
      "code": "sz.002039",
      "raw_code": "002039",
      "name": "黔源电力"
    },
    {
      "code": "sz.002046",
      "raw_code": "002046",
      "name": "国机精工"
    },
    {
      "code": "sz.002051",
      "raw_code": "002051",
      "name": "中工国际"
    },
    {
      "code": "sz.002057",
      "raw_code": "002057",
      "name": "中钢天源"
    },
    {
      "code": "sz.002059",
      "raw_code": "002059",
      "name": "云南旅游"
    },
    {
      "code": "sz.002063",
      "raw_code": "002063",
      "name": "远光软件"
    },
    {
      "code": "sz.002066",
      "raw_code": "002066",
      "name": "瑞泰科技"
    },
    {
      "code": "sz.002080",
      "raw_code": "002080",
      "name": "中材科技"
    },
    {
      "code": "sz.002096",
      "raw_code": "002096",
      "name": "易普力"
    },
    {
      "code": "sz.002116",
      "raw_code": "002116",
      "name": "中国海诚"
    },
    {
      "code": "sz.002128",
      "raw_code": "002128",
      "name": "电投能源"
    },
    {
      "code": "sz.002182",
      "raw_code": "002182",
      "name": "宝武镁业"
    },
    {
      "code": "sz.002189",
      "raw_code": "002189",
      "name": "中光学"
    },
    {
      "code": "sz.002205",
      "raw_code": "002205",
      "name": "国统股份"
    },
    {
      "code": "sz.002226",
      "raw_code": "002226",
      "name": "江南化工"
    },
    {
      "code": "sz.002232",
      "raw_code": "002232",
      "name": "启明信息"
    },
    {
      "code": "sz.002265",
      "raw_code": "002265",
      "name": "建设工业"
    },
    {
      "code": "sz.002281",
      "raw_code": "002281",
      "name": "光迅科技"
    },
    {
      "code": "sz.002302",
      "raw_code": "002302",
      "name": "西部建设"
    },
    {
      "code": "sz.002305",
      "raw_code": "002305",
      "name": "*ST南置"
    },
    {
      "code": "sz.002320",
      "raw_code": "002320",
      "name": "海峡股份"
    },
    {
      "code": "sz.002368",
      "raw_code": "002368",
      "name": "太极股份"
    },
    {
      "code": "sz.002389",
      "raw_code": "002389",
      "name": "航天彩虹"
    },
    {
      "code": "sz.002401",
      "raw_code": "002401",
      "name": "中远海科"
    },
    {
      "code": "sz.002415",
      "raw_code": "002415",
      "name": "海康威视"
    },
    {
      "code": "sz.002419",
      "raw_code": "002419",
      "name": "天虹股份"
    },
    {
      "code": "sz.002423",
      "raw_code": "002423",
      "name": "中粮资本"
    },
    {
      "code": "sz.002462",
      "raw_code": "002462",
      "name": "嘉事堂"
    },
    {
      "code": "sz.002916",
      "raw_code": "002916",
      "name": "深南电路"
    },
    {
      "code": "sz.002935",
      "raw_code": "002935",
      "name": "天奥电子"
    },
    {
      "code": "sz.002939",
      "raw_code": "002939",
      "name": "长城证券"
    },
    {
      "code": "sz.003009",
      "raw_code": "003009",
      "name": "中天火箭"
    },
    {
      "code": "sz.003031",
      "raw_code": "003031",
      "name": "中瓷电子"
    },
    {
      "code": "sz.003035",
      "raw_code": "003035",
      "name": "南网能源"
    },
    {
      "code": "sz.003816",
      "raw_code": "003816",
      "name": "中国广核"
    },
    {
      "code": "sz.300034",
      "raw_code": "300034",
      "name": "钢研高纳"
    },
    {
      "code": "sz.300070",
      "raw_code": "300070",
      "name": "碧水源"
    },
    {
      "code": "sz.300073",
      "raw_code": "300073",
      "name": "当升科技"
    },
    {
      "code": "sz.300087",
      "raw_code": "300087",
      "name": "ST荃银"
    },
    {
      "code": "sz.300105",
      "raw_code": "300105",
      "name": "龙源技术"
    },
    {
      "code": "sz.300140",
      "raw_code": "300140",
      "name": "节能环境"
    },
    {
      "code": "sz.300188",
      "raw_code": "300188",
      "name": "国投智能"
    },
    {
      "code": "sz.300197",
      "raw_code": "300197",
      "name": "节能铁汉"
    },
    {
      "code": "sz.300212",
      "raw_code": "300212",
      "name": "*ST易录"
    },
    {
      "code": "sz.300294",
      "raw_code": "300294",
      "name": "博雅生物"
    },
    {
      "code": "sz.300374",
      "raw_code": "300374",
      "name": "中铁装配"
    },
    {
      "code": "sz.300388",
      "raw_code": "300388",
      "name": "节能国祯"
    },
    {
      "code": "sz.300396",
      "raw_code": "300396",
      "name": "ST迪瑞"
    },
    {
      "code": "sz.300425",
      "raw_code": "300425",
      "name": "中建环能"
    },
    {
      "code": "sz.300446",
      "raw_code": "300446",
      "name": "航天智造"
    },
    {
      "code": "sz.300455",
      "raw_code": "300455",
      "name": "航天智装"
    },
    {
      "code": "sz.300516",
      "raw_code": "300516",
      "name": "久之洋"
    },
    {
      "code": "sz.300523",
      "raw_code": "300523",
      "name": "辰安科技"
    },
    {
      "code": "sz.300527",
      "raw_code": "300527",
      "name": "ST应急"
    },
    {
      "code": "sz.300557",
      "raw_code": "300557",
      "name": "理工光科"
    },
    {
      "code": "sz.300747",
      "raw_code": "300747",
      "name": "锐科激光"
    },
    {
      "code": "sz.300797",
      "raw_code": "300797",
      "name": "钢研纳克"
    },
    {
      "code": "sz.300847",
      "raw_code": "300847",
      "name": "中船汉光"
    },
    {
      "code": "sz.300962",
      "raw_code": "300962",
      "name": "中金辐照"
    },
    {
      "code": "sz.301048",
      "raw_code": "301048",
      "name": "金鹰重工"
    },
    {
      "code": "sz.301058",
      "raw_code": "301058",
      "name": "中粮科工"
    },
    {
      "code": "sz.301090",
      "raw_code": "301090",
      "name": "华润材料"
    },
    {
      "code": "sz.301137",
      "raw_code": "301137",
      "name": "哈焊华通"
    },
    {
      "code": "sz.301215",
      "raw_code": "301215",
      "name": "中汽股份"
    },
    {
      "code": "sz.301311",
      "raw_code": "301311",
      "name": "昆船智能"
    },
    {
      "code": "sz.301508",
      "raw_code": "301508",
      "name": "中机认检"
    },
    {
      "code": "sz.301638",
      "raw_code": "301638",
      "name": "南网数字"
    },
    {
      "code": "sz.302132",
      "raw_code": "302132",
      "name": "中航成飞"
    }
  ],
  "source": "ths_q_10jqka",
  "fetched_at": "2026-07-13 16:52:39",
  "page_count": 40,
  "is_partial": false,
  "page_limit_reason": null
}